pymlem/__init__.py
pymlem/pymlem.py
pymlem2-0.8.dist-info/METADATA
pymlem2-0.8.dist-info/WHEEL
pymlem2-0.8.dist-info/top_level.txt
pymlem2-0.8.dist-info/RECORD
