Metadata-Version: 2.4
Name: pymlem2
Version: 0.8
Summary: A brief description of your package
Author: kiminonawa
Author-email: kiminonawa@hotmal.com
Classifier: Programming Language :: Python :: 3
Classifier: License :: OSI Approved :: MIT License
Classifier: Operating System :: OS Independent
Requires-Python: >=3.6
Dynamic: author
Dynamic: author-email
Dynamic: classifier
Dynamic: requires-python
Dynamic: summary
